coingecko_exporter/__init__.py
coingecko_exporter/coingecko_exporter.py
coingecko_exporter-0.3.3.dist-info/METADATA
coingecko_exporter-0.3.3.dist-info/WHEEL
coingecko_exporter-0.3.3.dist-info/top_level.txt
coingecko_exporter-0.3.3.dist-info/RECORD
