Metadata-Version: 2.1
Name: coingecko_exporter
Version: 0.3.3
Summary: A package to export bulk data from the CoinGecko API.
Home-page: https://github.com/MattMaximo/coingecko_exporter
Author: Matt Maximo
Author-email: matt@pioneerdigital.org
Keywords: coingecko,crypto,data,api,exporter
Classifier: Programming Language :: Python :: 3
Classifier: License :: OSI Approved :: MIT License
Classifier: Operating System :: OS Independent
Requires-Python: >=3.6
Requires-Dist: httpx
Requires-Dist: pandas
Requires-Dist: duckdb
Requires-Dist: aiolimiter
Requires-Dist: pyarrow
Requires-Dist: fastparquet
Requires-Dist: boto3
